ipl_config/__init__.py
ipl_config/_optional_libs.py
ipl_config/dumploads.py
ipl_config/settings.py
ipl_config/source.py
ipl_config/utils.py
ipl_config-0.1.10.dist-info/entry_points.txt
ipl_config-0.1.10.dist-info/WHEEL
ipl_config-0.1.10.dist-info/METADATA
ipl_config-0.1.10.dist-info/RECORD
