Metadata-Version: 2.1
Name: ipl-config
Version: 0.1.10
Summary: InPlat config adapters
Home-page: https://github.com/koi8-r/ipl-config
License: MIT
Keywords: config,settings,pydantic,json,toml,yaml,hcl2
Author: InPlat
Requires-Python: >=3.7.2,<4.0.0
Classifier: Intended Audience :: Developers
Classifier: Intended Audience :: Information Technology
Classifier: Intended Audience :: System Administrators
Classifier: License :: OSI Approved :: MIT License
Classifier: Operating System :: OS Independent
Classifier: Programming Language :: Python :: 3
Classifier: Programming Language :: Python :: 3.8
Classifier: Programming Language :: Python :: 3.9
Classifier: Programming Language :: Python :: 3.10
Classifier: Programming Language :: Python :: 3
Classifier: Programming Language :: Python :: 3.10
Classifier: Programming Language :: Python :: 3.7
Classifier: Topic :: Internet
Classifier: Topic :: Software Development :: Libraries :: Python Modules
Provides-Extra: dotenv
Provides-Extra: hcl2
Provides-Extra: toml
Provides-Extra: yaml
Requires-Dist: pydantic (>=1.10.2,<2.0.0)
Requires-Dist: python-dotenv (>=0.21.0,<0.22.0); extra == "dotenv"
Requires-Dist: python-hcl2 (>=3.0.5,<4.0.0); extra == "hcl2"
Requires-Dist: pyyaml (>=5.0,<7.0); extra == "yaml"
Requires-Dist: toml (>=0.10.2,<0.11.0); extra == "toml"
Requires-Dist: typing-extensions (>=4.3.0,<5.0.0); python_version < "3.8"
Project-URL: Repository, https://github.com/koi8-r/ipl-config
